conjecture_sdk/__init__.py
conjecture_sdk/api.py
conjecture_sdk/chat_completion.py
conjecture_sdk/data_models.py
conjecture_sdk/model.py
conjecture_sdk-0.0.1.dist-info/METADATA
conjecture_sdk-0.0.1.dist-info/WHEEL
conjecture_sdk-0.0.1.dist-info/RECORD
